browser_manager/__init__.py
browser_manager/py.typed
browser_manager/bases/__init__.py
browser_manager/bases/browser.py
browser_manager/bases/browser_manager.py
browser_manager/bases/browser_selenium.py
browser_manager/browser/__init__.py
browser_manager/browser/chrome.py
browser_manager/browser/chromium.py
browser_manager/browser/firefox.py
browser_manager/browser/iexplore.py
browser_manager/browser/msedge.py
browser_manager/browser/opera.py
browser_manager/browser/safari.py
browser_manager/browser/selenium/__init__.py
browser_manager/browser/selenium/chrome.py
browser_manager/browser/selenium/chromium.py
browser_manager/browser/selenium/firefox.py
browser_manager/browser/selenium/iexplore.py
browser_manager/browser/selenium/msedge.py
browser_manager/browser/selenium/opera.py
browser_manager/browser/selenium/safari.py
browser_manager/interfaces/__init__.py
browser_manager/interfaces/browser.py
browser_manager/interfaces/browser_manager.py
browser_manager/interfaces/browser_selenium.py
browser_manager/manager/__init__.py
browser_manager/manager/selenium/__init__.py
browser_manager/utils/printer.py
browser_manager/utils/profile.py
browser_manager-1.0.5.dist-info/LICENSE
browser_manager-1.0.5.dist-info/METADATA
browser_manager-1.0.5.dist-info/WHEEL
browser_manager-1.0.5.dist-info/top_level.txt
browser_manager-1.0.5.dist-info/RECORD
