Metadata-Version: 2.2
Name: browser_manager
Version: 1.0.5
Summary: The BrowserManager Library simplifies browser automation and management...
Author-email: Dux Tecnologia <contato@tpereira.com.br>
License: MIT License
Project-URL: homepage, https://duxtec.github.io/browser-manager/docs
Project-URL: repository, https://github.com/duxtec/browser-manager
Project-URL: documentation, https://duxtec.github.io/browser-manager/docs
Classifier: Programming Language :: Python :: 3
Classifier: License :: OSI Approved :: MIT License
Classifier: Operating System :: OS Independent
Requires-Python: >=3.13
License-File: LICENSE
